inferadmin/__init__.py
inferadmin-0.0.1.dist-info/METADATA
inferadmin-0.0.1.dist-info/WHEEL
inferadmin-0.0.1.dist-info/entry_points.txt
inferadmin-0.0.1.dist-info/RECORD
