Metadata-Version: 2.4
Name: inferadmin
Version: 0.0.1
Summary: A lightweight management interface for local LLM infrastructure.
Author-email: TerminalMan <84923604+SecretiveShell@users.noreply.github.com>, Ben Gitter <gitterbd@gmail.com>
Requires-Python: >=3.11
Requires-Dist: fastapi>=0.115.12
Requires-Dist: uvicorn>=0.34.0
